[
    {
        "object_ids": [
            7,
            0,
            1
        ],
        "feature_num": 1,
        "deltas": [
            [
                -9.769273694933766
            ],
            [
                -41.2901202498977
            ],
            [
                -26.274298115961972
            ]
        ]
    },
    {
        "object_ids": [
            7,
            4,
            1,
            3,
            5,
            8,
            2
        ],
        "feature_num": 1,
        "deltas": [
            [
                1.2734956316987
            ],
            [
                32.93023871598476
            ],
            [
                4.080871367551078
            ],
            [
                -11.651299137509993
            ],
            [
                -11.575392892160927
            ],
            [
                1.3049417436226807
            ],
            [
                -35.68330119630211
            ]
        ]
    },
    {
        "object_ids": [
            2,
            1,
            8,
            6,
            0
        ],
        "feature_num": 1,
        "deltas": [
            [
                28.56377288660832
            ],
            [
                2.6839089204077493
            ],
            [
                -2.533481366711181
            ],
            [
                19.215989607623467
            ],
            [
                -12.120804609491973
            ]
        ]
    },
    {
        "object_ids": [
            3,
            0,
            7,
            8,
            1,
            4
        ],
        "feature_num": 1,
        "deltas": [
            [
                29.15592487521285
            ],
            [
                26.29514129582665
            ],
            [
                1.0493081833016915
            ],
            [
                8.798225477690742
            ],
            [
                -22.067539267999003
            ],
            [
                -24.730939918517187
            ]
        ]
    },
    {
        "object_ids": [
            0,
            4,
            5
        ],
        "feature_num": 1,
        "deltas": [
            [
                -22.623459373567307
            ],
            [
                34.01041042464957
            ],
            [
                -12.026301941108944
            ]
        ]
    },
    {
        "object_ids": [
            2,
            4,
            8,
            7,
            0,
            1,
            5,
            3
        ],
        "feature_num": 1,
        "deltas": [
            [
                -35.49680603452396
            ],
            [
                14.938066422241723
            ],
            [
                -3.699416108982474
            ],
            [
                -4.039320591709954
            ],
            [
                21.780928312431552
            ],
            [
                28.343239704170603
            ],
            [
                -4.429319195261051
            ],
            [
                30.728822518427194
            ]
        ]
    },
    {
        "object_ids": [
            3,
            8,
            7
        ],
        "feature_num": 1,
        "deltas": [
            [
                7.290352150126397
            ],
            [
                -4.537839684155274
            ],
            [
                3.391891186841607
            ]
        ]
    },
    {
        "object_ids": [
            4,
            8
        ],
        "feature_num": 1,
        "deltas": [
            [
                14.640214112353839
            ],
            [
                7.160795138403586
            ]
        ]
    },
    {
        "object_ids": [
            6,
            3,
            8,
            0,
            4,
            1,
            5
        ],
        "feature_num": 1,
        "deltas": [
            [
                5.8806919900732835
            ],
            [
                34.24552102965347
            ],
            [
                -9.21966993054802
            ],
            [
                39.30684670133978
            ],
            [
                12.992467112925427
            ],
            [
                -15.892922747707345
            ],
            [
                15.809515543328935
            ]
        ]
    },
    {
        "object_ids": [
            7,
            0,
            5,
            1
        ],
        "feature_num": 1,
        "deltas": [
            [
                -6.577267938542719
            ],
            [
                21.650744070350576
            ],
            [
                30.79709263801205
            ],
            [
                5.703875304554103
            ]
        ]
    },
    [
        144,
        145,
        146,
        147,
        148,
        149,
        150,
        151,
        152
    ],
    [
        16
    ]
]